pymysql_utils/__init__.py
pymysql_utils/pymysql_utils.py
pymysql_utils/test_framework.py
pymysql_utils/test_pymysql_utils.py
pymysql_utils/test_utils_config_parser.py
pymysql_utils/utils_config_parser.py
pymysql_utils-2.1.5.dist-info/METADATA
pymysql_utils-2.1.5.dist-info/WHEEL
pymysql_utils-2.1.5.dist-info/top_level.txt
pymysql_utils-2.1.5.dist-info/RECORD
