Metadata-Version: 2.1
Name: pymysql-utils
Version: 2.1.5
Summary: Thin wrapper around mysqlclient. Provides Python iterator for queries. Abstracts away cursor.
Home-page: https://github.com/paepcke/pymysql_utils
Author: Andreas Paepcke
Author-email: paepcke@cs.stanford.edu
License: BSD
Keywords: MySQL
Platform: UNKNOWN
Requires-Dist: mysqlclient (>=1.3.14)
Requires-Dist: PyMySQL (>=0.9.3)
Requires-Dist: configparser (>=3.3.0)
